{
  "objects": [
    {
      "type": "line",
      "equation": "y=-2x+2",
      "slope": -2,
      "intercept": 2,
      "value_at_1": 0
    }
  ],
  "image": "geometry_00073.png",
  "question": "[Rapid] Portugues: Informe inclinacao e intercepto da reta y=-2x+2.",
  "answer": "slope=-2, intercept=2",
  "qas": [
    {
      "question": "[Rapid] Portugues: Informe inclinacao e intercepto da reta y=-2x+2.",
      "answer": "slope=-2, intercept=2"
    },
    {
      "question": "[Rapid] Portugues: Informe inclinacao e intercepto da reta y=-2x+2. Provide only the slope.",
      "answer": "slope=-2"
    },
    {
      "question": "[Rapid] Portugues: Informe inclinacao e intercepto da reta y=-2x+2. Provide the intercept value.",
      "answer": "intercept=2"
    },
    {
      "question": "[Rapid] Portugues: Informe inclinacao e intercepto da reta y=-2x+2. Evaluate y when x=1.",
      "answer": "y=0.00"
    }
  ]
}