{
  "objects": [
    {
      "type": "rectangle",
      "coordinates": [
        28,
        68,
        73,
        140
      ],
      "area": 3240,
      "perimeter": 234,
      "width": 45,
      "height": 72,
      "diagonal": 84.91
    }
  ],
  "image": "geometry_00372.png",
  "question": "[Focus] Svenska: Ange area och omkrets for rektangeln med bredd 45 och hojd 72.",
  "answer": "area=3240, perimeter=234",
  "qas": [
    {
      "question": "[Focus] Svenska: Ange area och omkrets for rektangeln med bredd 45 och hojd 72.",
      "answer": "area=3240, perimeter=234"
    },
    {
      "question": "[Focus] Svenska: Ange area och omkrets for rektangeln med bredd 45 och hojd 72. Focus on the area value.",
      "answer": "area=3240"
    },
    {
      "question": "[Focus] Svenska: Ange area och omkrets for rektangeln med bredd 45 och hojd 72. Give the diagonal length.",
      "answer": "diagonal=84.91"
    }
  ]
}