{
  "objects": [
    {
      "type": "segment",
      "points": [
        [
          81,
          172
        ],
        [
          198,
          189
        ]
      ],
      "length": 118.23,
      "midpoint": [
        139.5,
        180.5
      ],
      "length_squared": 13978.0
    }
  ],
  "image": "geometry_00223.png",
  "question": "[Practice] English: Measure the length of segment from (81, 172) to (198, 189).",
  "answer": "length=118.23",
  "qas": [
    {
      "question": "[Practice] English: Measure the length of segment from (81, 172) to (198, 189).",
      "answer": "length=118.23"
    },
    {
      "question": "[Practice] English: Measure the length of segment from (81, 172) to (198, 189). Provide the squared length.",
      "answer": "length_squared=13978.00"
    },
    {
      "question": "[Practice] English: Measure the length of segment from (81, 172) to (198, 189). Provide the midpoint.",
      "answer": "midpoint=(139.50,180.50)"
    }
  ]
}