{
  "objects": [
    {
      "type": "line",
      "equation": "y=2x+1",
      "slope": 2,
      "intercept": 1,
      "value_at_1": 3
    }
  ],
  "image": "geometry_00081.png",
  "question": "[Focus] Nederlands: Geef helling en intercept van de lijn y=2x+1.",
  "answer": "slope=2, intercept=1",
  "qas": [
    {
      "question": "[Focus] Nederlands: Geef helling en intercept van de lijn y=2x+1.",
      "answer": "slope=2, intercept=1"
    },
    {
      "question": "[Focus] Nederlands: Geef helling en intercept van de lijn y=2x+1. Provide only the slope.",
      "answer": "slope=2"
    },
    {
      "question": "[Focus] Nederlands: Geef helling en intercept van de lijn y=2x+1. Provide the intercept value.",
      "answer": "intercept=1"
    },
    {
      "question": "[Focus] Nederlands: Geef helling en intercept van de lijn y=2x+1. Evaluate y when x=1.",
      "answer": "y=3.00"
    }
  ]
}